filelogr/__init__.py
filelogr/filelogr.py
filelogr-1.2.1.dist-info/licenses/LICENSE
filelogr-1.2.1.dist-info/METADATA
filelogr-1.2.1.dist-info/WHEEL
filelogr-1.2.1.dist-info/top_level.txt
filelogr-1.2.1.dist-info/RECORD
