Metadata-Version: 2.4
Name: filelogr
Version: 1.2.1
Summary: A flexible logging utility for your Python projects
Author: Futuregus
License-Expression: MIT
Project-URL: Homepage, https://github.com/Futuregus/filelogr
Project-URL: Bug_Tracker, https://github.com/Futuregus/filelogr/issues
License-File: LICENSE
Dynamic: license-file
